visokio_omniprint/DriverBase.py
visokio_omniprint/Image.py
visokio_omniprint/ImagesPPTX.py
visokio_omniprint/ImagesPdf.py
visokio_omniprint/Pdf.py
visokio_omniprint/Tools.py
visokio_omniprint/__about__.py
visokio_omniprint/__init__.py
visokio_omniprint-1.3.4.dist-info/METADATA
visokio_omniprint-1.3.4.dist-info/WHEEL
visokio_omniprint-1.3.4.dist-info/licenses/LICENSE
visokio_omniprint-1.3.4.dist-info/RECORD
