Metadata-Version: 2.1
Name: visokio-omniprint
Version: 1.3.4
Summary: Visokio Omniscope PDF printing library
Project-URL: Documentation, https://github.com/visokio/omniscope-custom-blocks/tree/master/visokio-omniprint#readme
Project-URL: Issues, https://github.com/visokio/omniscope-custom-blocks/tree/master/visokio-omniprint/issues
Project-URL: Source, https://github.com/visokio/omniscope-custom-blocks/tree/master/visokio-omniprint
Author: Visokio
License-Expression: MIT
License-File: LICENSE
Classifier: Development Status :: 4 - Beta
Classifier: Programming Language :: Python
Classifier: Programming Language :: Python :: 3.7
Classifier: Programming Language :: Python :: 3.8
Classifier: Programming Language :: Python :: 3.9
Classifier: Programming Language :: Python :: 3.10
Classifier: Programming Language :: Python :: 3.11
Classifier: Programming Language :: Python :: Implementation :: CPython
Classifier: Programming Language :: Python :: Implementation :: PyPy
Requires-Python: >=3.7
Requires-Dist: fpdf
Requires-Dist: get-chrome-driver>=1.3.19
Requires-Dist: python-pptx
Requires-Dist: selenium>=4.26.0
Requires-Dist: tinify
Requires-Dist: urllib3
Requires-Dist: webdriver-manager
